blokus_rl-0.2.6.dist-info/METADATA
blokus_rl-0.2.6.dist-info/WHEEL
blokus_rl-0.2.6.dist-info/licenses/LICENSE
blokus_rl/api_test.py
blokus_rl/__init__.py
blokus_rl/blokus_env.py
blokus_rl/_blokus.cpython-310-x86_64-linux-gnu.so
blokus_rl-0.2.6.dist-info/RECORD
