Metadata-Version: 2.4
Name: blokus-rl
Version: 0.2.6
Classifier: Programming Language :: Rust
Classifier: Programming Language :: Python :: Implementation :: CPython
Classifier: Programming Language :: Python :: Implementation :: PyPy
Requires-Dist: pettingzoo==1.24.2
Requires-Dist: pygame==2.5.2
License-File: LICENSE
Requires-Python: >=3.10
